<?xml version="1.0" encoding="utf-8" ?>
<NPCCharacters>
	<!-- Vampire Counts Basic troop tree-->
	<!-- Vampire Counts animated skeleton-->
	<NPCCharacter id="tow_skeleton_recruit"
			default_group="Infantry"
			level="6"
			name="{=!}Animated Skeleton"
			occupation="Soldier"
			is_basic_troop="true"
			culture="Culture.khuzait"
			skill_template="SkillSet.tow_skills_level6">
		<face>
			<face_key_template value="BodyProperty.fighter_khuzait" />
		</face>
		<upgrade_targets>
			<upgrade_target id="NPCCharacter.tow_skeleton_warrior" />
			<upgrade_target id="NPCCharacter.tow_skeleton_spearmen" />
		</upgrade_targets>
		<Equipments>
			<EquipmentRoster>
				<equipment slot="Item0"
						   id="Item.skeleton_warrior_sword_002" />
				<equipment slot="Body"
						   id="Item.skeleton_body_full" />
			</EquipmentRoster>
			<EquipmentRoster>
				<equipment slot="Item0"
						   id="Item.skeleton_warrior_sword_001" />
				<equipment slot="Body"
						   id="Item.skeleton_body_glowing_full" />
			</EquipmentRoster>
		</Equipments>
	</NPCCharacter>
	<!-- Vampire Counts skeleton warrior-->
	<NPCCharacter id="tow_skeleton_warrior"
			default_group="Infantry"
			level="11"
			name="{=!}Skeleton Warrior"
			occupation="Soldier"
			is_basic_troop="true"
			culture="Culture.khuzait"
			skill_template="SkillSet.tow_skills_level11">
		<face>
			<face_key_template value="BodyProperty.fighter_khuzait" />
		</face>
		<upgrade_targets>
		</upgrade_targets>
		<Equipments>
			<EquipmentRoster>
				<equipment slot="Item0"
						   id="Item.skeleton_warrior_sword_002" />
				<equipment slot="Item1"
						   id="Item.skeleton_warrior_shield_002" />
				<equipment slot="Body"
						   id="Item.skeleton_body_glowing_full" />
			</EquipmentRoster>
			<EquipmentRoster>
				<equipment slot="Item0"
						   id="Item.skeleton_warrior_sword_001" />
				<equipment slot="Item1"
						   id="Item.skeleton_warrior_shield_001" />
				<equipment slot="Body"
						   id="Item.skeleton_body_glowing_full" />
			</EquipmentRoster>
			<EquipmentRoster>
				<equipment slot="Item0"
						   id="Item.skeleton_warrior_sword_002" />
				<equipment slot="Item1"
						   id="Item.skeleton_warrior_shield_003" />
				<equipment slot="Body"
						   id="Item.skeleton_body_glowing_full" />
			</EquipmentRoster>
			<EquipmentRoster>
				<equipment slot="Item0"
						   id="Item.skeleton_warrior_sword_001" />
				<equipment slot="Item1"
						   id="Item.skeleton_warrior_shield_004" />
				<equipment slot="Body"
						   id="Item.skeleton_body_glowing_full" />
			</EquipmentRoster>
			<EquipmentRoster>
				<equipment slot="Item0"
						   id="Item.skeleton_warrior_sword_002" />
				<equipment slot="Item1"
						   id="Item.skeleton_warrior_shield_005" />
				<equipment slot="Body"
						   id="Item.skeleton_body_glowing_full" />
			</EquipmentRoster>
			<EquipmentRoster>
				<equipment slot="Item0"
						   id="Item.skeleton_warrior_sword_001" />
				<equipment slot="Item1"
						   id="Item.skeleton_warrior_shield_007" />
				<equipment slot="Body"
						   id="Item.skeleton_body_glowing_full" />
			</EquipmentRoster>
		</Equipments>
	</NPCCharacter>
	<!-- Vampire Counts skeleton spearman-->
	<NPCCharacter id="tow_skeleton_spearman"
			default_group="Infantry"
			level="11"
			name="{=!}Skeleton Spearman"
			occupation="Soldier"
			is_basic_troop="true"
			culture="Culture.khuzait"
			skill_template="SkillSet.tow_skills_level11">
		<face>
			<face_key_template value="BodyProperty.fighter_khuzait" />
		</face>
		<upgrade_targets>
		</upgrade_targets>
		<Equipments>
			<EquipmentRoster>
				<equipment slot="Item0"
						   id="Item.skeleton_warrior_sword_002" />
				<equipment slot="Item1"
						   id="Item.skeleton_warrior_shield_002" />
				<equipment slot="Body"
						   id="Item.skeleton_body_glowing_full" />
			</EquipmentRoster>
			<EquipmentRoster>
				<equipment slot="Item0"
						   id="Item.skeleton_warrior_sword_001" />
				<equipment slot="Item1"
						   id="Item.skeleton_warrior_shield_001" />
				<equipment slot="Body"
						   id="Item.skeleton_body_glowing_full" />
			</EquipmentRoster>
			<EquipmentRoster>
				<equipment slot="Item0"
						   id="Item.skeleton_warrior_sword_002" />
				<equipment slot="Item1"
						   id="Item.skeleton_warrior_shield_003" />
				<equipment slot="Body"
						   id="Item.skeleton_body_glowing_full" />
			</EquipmentRoster>
			<EquipmentRoster>
				<equipment slot="Item0"
						   id="Item.skeleton_warrior_sword_001" />
				<equipment slot="Item1"
						   id="Item.skeleton_warrior_shield_004" />
				<equipment slot="Body"
						   id="Item.skeleton_body_glowing_full" />
			</EquipmentRoster>
			<EquipmentRoster>
				<equipment slot="Item0"
						   id="Item.skeleton_warrior_sword_002" />
				<equipment slot="Item1"
						   id="Item.skeleton_warrior_shield_005" />
				<equipment slot="Body"
						   id="Item.skeleton_body_glowing_full" />
			</EquipmentRoster>
			<EquipmentRoster>
				<equipment slot="Item0"
						   id="Item.skeleton_warrior_sword_001" />
				<equipment slot="Item1"
						   id="Item.skeleton_warrior_shield_007" />
				<equipment slot="Body"
						   id="Item.skeleton_body_glowing_full" />
			</EquipmentRoster>
		</Equipments>
	</NPCCharacter>
</NPCCharacters>